odoo9_addon_sales_team_multicompany-9.0.1.0.0.99.dev8-py2.7-nspkg.pth
odoo9_addon_sales_team_multicompany-9.0.1.0.0.99.dev8.dist-info/DESCRIPTION.rst
odoo9_addon_sales_team_multicompany-9.0.1.0.0.99.dev8.dist-info/METADATA
odoo9_addon_sales_team_multicompany-9.0.1.0.0.99.dev8.dist-info/RECORD
odoo9_addon_sales_team_multicompany-9.0.1.0.0.99.dev8.dist-info/WHEEL
odoo9_addon_sales_team_multicompany-9.0.1.0.0.99.dev8.dist-info/metadata.json
odoo9_addon_sales_team_multicompany-9.0.1.0.0.99.dev8.dist-info/namespace_packages.txt
odoo9_addon_sales_team_multicompany-9.0.1.0.0.99.dev8.dist-info/top_level.txt
odoo_addons/sales_team_multicompany/README.rst
odoo_addons/sales_team_multicompany/__init__.py
odoo_addons/sales_team_multicompany/__openerp__.py
odoo_addons/sales_team_multicompany/hooks.py
odoo_addons/sales_team_multicompany/sales_team.py
odoo_addons/sales_team_multicompany/sales_team.xml
odoo_addons/sales_team_multicompany/sales_team_multicompany_demo.xml
odoo_addons/sales_team_multicompany/i18n/de.po
odoo_addons/sales_team_multicompany/i18n/es.po
odoo_addons/sales_team_multicompany/i18n/fr.po
odoo_addons/sales_team_multicompany/i18n/sales_team_multicompany.pot
odoo_addons/sales_team_multicompany/security/sales_team_multicompany_security.xml
odoo_addons/sales_team_multicompany/static/description/icon.png
odoo_addons/sales_team_multicompany/tests/__init__.py
odoo_addons/sales_team_multicompany/tests/test_sales_team_multicompany.py
